[
  {
    "name": "スーパーで一番高い<wbr>弁当を買う",
    "cost": "千円",
    "effort": "すぐできる"
  },
  {
    "name": "夜中にハーゲンダッツを食べる",
    "cost": "数百円",
    "effort": "すぐできる"
  },
  {
    "name": "知らない駅で下車して<wbr>5分だけ歩く",
    "cost": "数百円",
    "effort": "すぐできる"
  },
  {
    "name": "見知らぬカフェに行く",
    "cost": "千円",
    "effort": "すぐできる"
  },
  {
    "name": "お弁当作ってお花見をする",
    "cost": "千円",
    "effort": "半日かかる"
  },
  {
    "name": "コンビニのアイス<wbr>全種類買う",
    "cost": "数千円",
    "effort": "すぐできる"
  },
  {
    "name": "タクシー代を出し合って<wbr>行けるとこまで行ってもらう",
    "cost": "一万円以上",
    "effort": "半日かかる"
  },
  {
    "name": "ブランコに乗る",
    "cost": "0円",
    "effort": "すぐできる"
  },
  {
    "name": "本気でケイドロする",
    "cost": "0円",
    "effort": "すぐできる"
  },
  {
    "name": "レイトショーを見に行く",
    "cost": "数千円",
    "effort": "半日かかる"
  },
  {
    "name": "海を見に行く",
    "cost": "数百円",
    "effort": "半日かかる"
  },
  {
    "name": "友達とやりたいことリスト50",
    "cost": "0円",
    "effort": "すぐできる"
  },
  {
    "name": "駄菓子屋で1人1000円分<wbr>好きなものを買う",
    "cost": "千円",
    "effort": "すぐできる"
  },
  {
    "name": "始発列車に乗って<wbr>日の出を見に行く",
    "cost": "数百円",
    "effort": "半日かかる"
  },
  {
    "name": "終電を逃して<wbr>朝までカラオケ",
    "cost": "数千円",
    "effort": "半日かかる"
  },
  {
    "name": "公園で本気で<wbr>シャボン玉を飛ばす",
    "cost": "数百円",
    "effort": "すぐできる"
  },
  {
    "name": "食べ放題で全メニュー<wbr>制覇に挑戦",
    "cost": "数千円",
    "effort": "半日かかる"
  },
  {
    "name": "お揃いのキーホルダーを買う",
    "cost": "千円",
    "effort": "すぐできる"
  },
  {
    "name": "一緒に餃子パをする",
    "cost": "数千円",
    "effort": "半日かかる"
  },
  {
    "name": "一緒にたこパをする",
    "cost": "数千円",
    "effort": "半日かかる"
  },
  {
    "name": "一緒に鍋パをする",
    "cost": "数千円",
    "effort": "半日かかる"
  },
  {
    "name": "一緒に焼肉をする",
    "cost": "数千円",
    "effort": "半日かかる"
  },
  {
    "name": "一緒にピザパをする",
    "cost": "数千円",
    "effort": "半日かかる"
  },
  {
    "name": "一緒に寿司パをする",
    "cost": "数千円",
    "effort": "半日かかる"
  },
  {
    "name": "一緒にお好み焼きをする",
    "cost": "数千円",
    "effort": "半日かかる"
  },
  {
    "name": "一緒にもんじゃをする",
    "cost": "数千円",
    "effort": "半日かかる"
  },
  {
    "name": "知らない商店街で食べ歩き",
    "cost": "数千円",
    "effort": "半日かかる"
  },
  {
    "name": "占いをハシゴして<wbr>結果を比べる",
    "cost": "数千円",
    "effort": "半日かかる"
  },
  {
    "name": "24時間営業のファミレスで<wbr>夜通し語り合う",
    "cost": "千円",
    "effort": "半日かかる"
  },
  {
    "name": "豪華なホテルの<wbr>アフタヌーンティーを体験",
    "cost": "数千円",
    "effort": "半日かかる"
  },
  {
    "name": "動物園で一番面白い<wbr>動物の写真を撮る",
    "cost": "数千円",
    "effort": "半日かかる"
  },
  {
    "name": "水族館の巨大水槽の前で<wbr>ぼーっとする",
    "cost": "数千円",
    "effort": "半日かかる"
  },
  {
    "name": "ボードゲームカフェで<wbr>一日中遊ぶ",
    "cost": "数千円",
    "effort": "一日かかる"
  },
  {
    "name": "全力で変顔のプリクラを撮る",
    "cost": "数百円",
    "effort": "すぐできる"
  },
  {
    "name": "日帰り温泉で卓球対決",
    "cost": "数千円",
    "effort": "半日かかる"
  },
  {
    "name": "おしゃピクをする",
    "cost": "千円",
    "effort": "半日かかる"
  },
  {
    "name": "川辺で水切り石が<wbr>何回できるか競う",
    "cost": "0円",
    "effort": "すぐできる"
  },
  {
    "name": "パン屋巡り",
    "cost": "千円",
    "effort": "半日かかる"
  },
  {
    "name": "百均で「一番使えそうなもの」を<wbr>買い合ってプレゼント交換",
    "cost": "数百円",
    "effort": "すぐできる"
  },
  {
    "name": "百均で「一番要らないもの」を<wbr>買い合ってプレゼント交換",
    "cost": "数百円",
    "effort": "すぐできる"
  },
  {
    "name": "ちょっとした山に登って<wbr>お弁当を食べる",
    "cost": "千円",
    "effort": "半日かかる"
  },
  {
    "name": "バッティングセンターで<wbr>ホームランを狙う",
    "cost": "千円",
    "effort": "すぐできる"
  },
  {
    "name": "図書館で一日中、<wbr>普段読まないジャンルの本を読む",
    "cost": "0円",
    "effort": "一日かかる"
  },
  {
    "name": "古着屋でお互いの服を<wbr>本気でコーディネートし合う",
    "cost": "数千円",
    "effort": "半日かかる"
  },
  {
    "name": "レンタサイクルで<wbr>知らない街を走る",
    "cost": "千円",
    "effort": "半日かかる"
  },
  {
    "name": "ダーツやビリヤードに挑戦",
    "cost": "数千円",
    "effort": "半日かかる"
  },
  {
    "name": "ビール工場やワイナリーの<wbr>見学に行く",
    "cost": "数千円",
    "effort": "半日かかる"
  },
  {
    "name": "3000円でどれだけ<wbr>オシャレできるか勝負",
    "cost": "数千円",
    "effort": "半日かかる"
  },
  {
    "name": "ラーメン屋ハシゴ",
    "cost": "数千円",
    "effort": "半日かかる"
  },
  {
    "name": "遊園地で絶叫マシンだけ<wbr>乗りまくる",
    "cost": "一万円",
    "effort": "一日かかる"
  },
  {
    "name": "砂浜で本気で砂の城を作る",
    "cost": "数百円",
    "effort": "半日かかる"
  },
  {
    "name": "砂浜で本気で穴を掘る",
    "cost": "数百円",
    "effort": "半日かかる"
  },
  {
    "name": "好きな映画やドラマの<wbr>聖地巡礼",
    "cost": "数千円",
    "effort": "一日かかる"
  },
  {
    "name": "1年後の自分たちへ向けて<wbr>タイムカプセルや手紙を埋める",
    "cost": "数百円",
    "effort": "すぐできる"
  },
  {
    "name": "1万円握りしめて<wbr>パチンコに行ってみる",
    "cost": "一万円",
    "effort": "半日かかる"
  },
  {
    "name": "高級バーでカクテルを<wbr>一杯だけ飲む",
    "cost": "数千円",
    "effort": "すぐできる"
  },
  {
    "name": "路線バスで終点まで<wbr>行ってみる",
    "cost": "千円",
    "effort": "半日かかる"
  },
  {
    "name": "陶芸体験でお揃いの<wbr>コップを作る",
    "cost": "数千円",
    "effort": "半日かかる"
  },
  {
    "name": "釣り堀で釣れるまで帰らない",
    "cost": "数千円",
    "effort": "半日かかる"
  },
  {
    "name": "スワンボートに乗る",
    "cost": "千円",
    "effort": "すぐできる"
  },
  {
    "name": "激辛グルメに挑戦",
    "cost": "数千円",
    "effort": "半日かかる"
  },
  {
    "name": "一日中パジャマで過ごして<wbr>デリバリーパーティー",
    "cost": "数千円",
    "effort": "一日かかる"
  },
  {
    "name": "一緒にDIYに挑戦",
    "cost": "数千円",
    "effort": "一日かかる"
  },
  {
    "name": "サバゲー体験",
    "cost": "数千円",
    "effort": "一日かかる"
  },
  {
    "name": "漫画喫茶のペアシートで<wbr>一日中だらだらする",
    "cost": "数千円",
    "effort": "一日かかる"
  },
  {
    "name": "劇団四季を観に行く",
    "cost": "一万円以上",
    "effort": "半日かかる"
  },
  {
    "name": "ディズニー食べ歩き",
    "cost": "一万円以上",
    "effort": "一日かかる"
  },
  {
    "name": "私服姿のバウンドコーデを<wbr>してみる",
    "cost": "数千円",
    "effort": "半日かかる"
  },
  {
    "name": "個展に行く",
    "cost": "千円",
    "effort": "半日かかる"
  },
  {
    "name": "一緒に映画鑑賞",
    "cost": "数千円",
    "effort": "半日かかる"
  },
  {
    "name": "隣駅まで歩く",
    "cost": "0円",
    "effort": "すぐできる"
  },
  {
    "name": "みんなのおすすめ<wbr>YouTuberを観る",
    "cost": "0円",
    "effort": "すぐできる"
  },
  {
    "name": "レンタカー借りてIKEAに行く",
    "cost": "数千円",
    "effort": "一日かかる"
  },
  {
    "name": "温泉旅行に行く",
    "cost": "一万円以上",
    "effort": "一日かかる"
  },
  {
    "name": "夜ドライブで夜景を見る",
    "cost": "数千円",
    "effort": "半日かかる"
  },
  {
    "name": "隣県まで旅行",
    "cost": "一万円以上",
    "effort": "一日かかる"
  },
  {
    "name": "食べログ高評価のお店に行く",
    "cost": "数千円",
    "effort": "半日かかる"
  },
  {
    "name": "トルコ料理を食べる",
    "cost": "数千円",
    "effort": "半日かかる"
  },
  {
    "name": "メキシコ料理を食べる",
    "cost": "数千円",
    "effort": "半日かかる"
  },
  {
    "name": "パキスタン料理を食べる",
    "cost": "数千円",
    "effort": "半日かかる"
  },
  {
    "name": "ハンガリー料理を食べる",
    "cost": "数千円",
    "effort": "半日かかる"
  },
  {
    "name": "台湾料理を食べる",
    "cost": "数千円",
    "effort": "半日かかる"
  },
  {
    "name": "スポッチャで全アトラクション<wbr>制覇に挑戦",
    "cost": "数千円",
    "effort": "一日かかる"
  },
  {
    "name": "お互いの似顔絵を<wbr>本気で描いて交換する",
    "cost": "数百円",
    "effort": "すぐできる"
  },
  {
    "name": "テレビゲーム大会",
    "cost": "0円",
    "effort": "半日かかる"
  },
  {
    "name": "協力して巨大ジグソー<wbr>パズルを完成させる",
    "cost": "数千円",
    "effort": "一日かかる"
  },
  {
    "name": "手ぶらでキャンプ体験",
    "cost": "一万円",
    "effort": "一日かかる"
  },
  {
    "name": "落語や寄席を観に行く",
    "cost": "数千円",
    "effort": "半日かかる"
  },
  {
    "name": "美術館巡り",
    "cost": "数千円",
    "effort": "一日かかる"
  },
  {
    "name": "博物館巡り",
    "cost": "数千円",
    "effort": "一日かかる"
  },
  {
    "name": "お城巡り",
    "cost": "数千円",
    "effort": "一日かかる"
  },
  {
    "name": "スーパー銭湯で一日中過ごす",
    "cost": "数千円",
    "effort": "一日かかる"
  },
  {
    "name": "利きポテチ大会",
    "cost": "千円",
    "effort": "すぐできる"
  },
  {
    "name": "利きチョコ大会",
    "cost": "千円",
    "effort": "すぐできる"
  },
  {
    "name": "近所の猫を探す",
    "cost": "0円",
    "effort": "すぐできる"
  },
  {
    "name": "3000円でゲーセンを遊び倒す",
    "cost": "数千円",
    "effort": "半日かかる"
  },
  {
    "name": "マック1万円分爆買い",
    "cost": "一万円",
    "effort": "すぐできる"
  },
  {
    "name": "人間観察",
    "cost": "0円",
    "effort": "すぐできる"
  },
  {
    "name": "ゲーセンで3000円使う",
    "cost": "数千円",
    "effort": "半日かかる"
  },
  {
    "name": "真夜の公園でラジオ体操",
    "cost": "0円",
    "effort": "すぐできる"
  },
  {
    "name": "炊飯器で大きな<wbr>ハンバーグを作る",
    "cost": "千円",
    "effort": "半日かかる"
  },
  {
    "name": "炊飯器で大きなたこ焼きを作る",
    "cost": "千円",
    "effort": "半日かかる"
  },
  {
    "name": "家で本格スイーツ作り",
    "cost": "数千円",
    "effort": "半日かかる"
  },
  {
    "name": "業スー縛り<wbr>フルコースディナーを作る",
    "cost": "数千円",
    "effort": "半日かかる"
  },
  {
    "name": "近くの観光地に行って<wbr>1番ダサいお土産を買う",
    "cost": "千円",
    "effort": "半日かかる"
  },
  {
    "name": "駅でサイコロを振って<wbr>出た目の数だけ<wbr>電車で進んで探索する",
    "cost": "数千円",
    "effort": "一日かかる"
  },
  {
    "name": "米のないカレーライスを作る",
    "cost": "千円",
    "effort": "半日かかる"
  },
  {
    "name": "卵のないオムライスを作る",
    "cost": "千円",
    "effort": "半日かかる"
  },
  {
    "name": "タコのないたこ焼きを作る",
    "cost": "千円",
    "effort": "半日かかる"
  },
  {
    "name": "好きな曲のMVを勝手に作る",
    "cost": "0円",
    "effort": "一日かかる"
  }
]
